{
  "school": {
    "schoolCode": "10010",
    "schoolName": "北京化工大学",
    "schoolTotalPlan": null,
    "schoolLocation": "北京市",
    "consultPhone": "010-64435706",
    "programCount": 5,
    "track": "history"
  },
  "programs": [
    {
      "track": "history",
      "batchName": "本科提前批其他三类",
      "schoolCode": "10010",
      "schoolName": "北京化工大学",
      "schoolTotalPlan": null,
      "schoolLocation": "北京市",
      "consultPhone": "010-64435706",
      "majorGroupCode": "619",
      "majorGroupPlan": null,
      "firstSubject": "历史",
      "secondSubject": "不限",
      "majorCode": "001",
      "majorName": "社会体育指导与管理",
      "planCount": "以高校公布计划为准",
      "durationYears": 4,
      "tuitionPerYear": 5000,
      "campus": "朝阳校区/昌平校区办学",
      "remarks": "高水平运动队，4年，5000元/年，在朝阳校区/昌平校区办学",
      "pdfPage": 129,
      "bookPage": 79
    },
    {
      "track": "history",
      "batchName": "本科普通批",
      "schoolCode": "10010",
      "schoolName": "北京化工大学",
      "schoolTotalPlan": null,
      "schoolLocation": "北京市",
      "consultPhone": "010-64435706",
      "majorGroupCode": "106",
      "majorGroupPlan": 12,
      "firstSubject": "历史",
      "secondSubject": "不限",
      "majorCode": "022",
      "majorName": "法学",
      "planCount": 3,
      "durationYears": 4,
      "tuitionPerYear": 5000,
      "campus": "朝阳校区/昌平校区办学",
      "remarks": "4 年,5000 元/年,在朝阳校区/昌平校区办学",
      "pdfPage": 136,
      "bookPage": 86
    },
    {
      "track": "history",
      "batchName": "本科普通批",
      "schoolCode": "10010",
      "schoolName": "北京化工大学",
      "schoolTotalPlan": null,
      "schoolLocation": "北京市",
      "consultPhone": "010-64435706",
      "majorGroupCode": "106",
      "majorGroupPlan": 12,
      "firstSubject": "历史",
      "secondSubject": "不限",
      "majorCode": "023",
      "majorName": "工商管理类(数字财务与智能会计)",
      "planCount": 6,
      "durationYears": 4,
      "tuitionPerYear": 5000,
      "campus": "朝阳校区/昌平校区办学",
      "remarks": "4年，5000元/年，在朝阳校区/昌平校区办学，包含专业：工商管理、财务管理、会计学",
      "pdfPage": 136,
      "bookPage": 86
    },
    {
      "track": "history",
      "batchName": "本科普通批",
      "schoolCode": "10010",
      "schoolName": "北京化工大学",
      "schoolTotalPlan": null,
      "schoolLocation": "北京市",
      "consultPhone": "010-64435706",
      "majorGroupCode": "106",
      "majorGroupPlan": 12,
      "firstSubject": "历史",
      "secondSubject": "不限",
      "majorCode": "024",
      "majorName": "公共事业管理",
      "planCount": 1,
      "durationYears": 4,
      "tuitionPerYear": 5000,
      "campus": "朝阳校区/昌平校区办学",
      "remarks": "4 年,5000 元/年,在朝阳校区/昌平校区办学",
      "pdfPage": 136,
      "bookPage": 86
    },
    {
      "track": "history",
      "batchName": "本科普通批",
      "schoolCode": "10010",
      "schoolName": "北京化工大学",
      "schoolTotalPlan": null,
      "schoolLocation": "北京市",
      "consultPhone": "010-64435706",
      "majorGroupCode": "106",
      "majorGroupPlan": 12,
      "firstSubject": "历史",
      "secondSubject": "不限",
      "majorCode": "025",
      "majorName": "行政管理",
      "planCount": 2,
      "durationYears": 4,
      "tuitionPerYear": 5000,
      "campus": "朝阳校区/昌平校区办学",
      "remarks": "4 年,5000 元/年,在朝阳校区/昌平校区办学",
      "pdfPage": 136,
      "bookPage": 86
    }
  ]
}
