{
  "school": {
    "schoolCode": "10518",
    "schoolName": "汉江师范学院",
    "schoolTotalPlan": 12,
    "schoolLocation": "湖北省十堰市",
    "consultPhone": "0719-8846111、8846222",
    "programCount": 20,
    "track": "history"
  },
  "programs": [
    {
      "track": "history",
      "batchName": "本科提前批艺术类本科第二批",
      "schoolCode": "10518",
      "schoolName": "汉江师范学院",
      "schoolTotalPlan": 12,
      "schoolLocation": "湖北省十堰市",
      "consultPhone": "0719-8846111、8846222",
      "majorGroupCode": "206",
      "majorGroupPlan": 4,
      "firstSubject": "历史",
      "secondSubject": "不限",
      "majorCode": "001",
      "majorName": "美术学",
      "planCount": 2,
      "durationYears": 4,
      "tuitionPerYear": 10350,
      "campus": null,
      "remarks": "美术与设计类,师范类,4 年,10350 元/年",
      "pdfPage": 73,
      "bookPage": 23
    },
    {
      "track": "history",
      "batchName": "本科提前批艺术类本科第二批",
      "schoolCode": "10518",
      "schoolName": "汉江师范学院",
      "schoolTotalPlan": 12,
      "schoolLocation": "湖北省十堰市",
      "consultPhone": "0719-8846111、8846222",
      "majorGroupCode": "206",
      "majorGroupPlan": 4,
      "firstSubject": "历史",
      "secondSubject": "不限",
      "majorCode": "002",
      "majorName": "绘画",
      "planCount": 2,
      "durationYears": 4,
      "tuitionPerYear": 10350,
      "campus": null,
      "remarks": "美术与设计类,4 年,10350 元/年",
      "pdfPage": 73,
      "bookPage": 23
    },
    {
      "track": "history",
      "batchName": "本科提前批艺术类本科第二批",
      "schoolCode": "10518",
      "schoolName": "汉江师范学院",
      "schoolTotalPlan": 12,
      "schoolLocation": "湖北省十堰市",
      "consultPhone": "0719-8846111、8846222",
      "majorGroupCode": "207",
      "majorGroupPlan": 2,
      "firstSubject": "历史",
      "secondSubject": "不限",
      "majorCode": "003",
      "majorName": "数字媒体艺术",
      "planCount": 2,
      "durationYears": 4,
      "tuitionPerYear": 10350,
      "campus": null,
      "remarks": "美术与设计类,4 年,10350 元/年",
      "pdfPage": 73,
      "bookPage": 23
    },
    {
      "track": "history",
      "batchName": "本科提前批艺术类本科第二批",
      "schoolCode": "10518",
      "schoolName": "汉江师范学院",
      "schoolTotalPlan": 12,
      "schoolLocation": "湖北省十堰市",
      "consultPhone": "0719-8846111、8846222",
      "majorGroupCode": "208",
      "majorGroupPlan": 2,
      "firstSubject": "历史",
      "secondSubject": "不限",
      "majorCode": "004",
      "majorName": "音乐学",
      "planCount": 2,
      "durationYears": 4,
      "tuitionPerYear": 10350,
      "campus": null,
      "remarks": "音乐类（音乐教育）,师范类,4 年,10350 元/年",
      "pdfPage": 73,
      "bookPage": 23
    },
    {
      "track": "history",
      "batchName": "本科提前批艺术类本科第二批",
      "schoolCode": "10518",
      "schoolName": "汉江师范学院",
      "schoolTotalPlan": 12,
      "schoolLocation": "湖北省十堰市",
      "consultPhone": "0719-8846111、8846222",
      "majorGroupCode": "209",
      "majorGroupPlan": 2,
      "firstSubject": "历史",
      "secondSubject": "不限",
      "majorCode": "005",
      "majorName": "舞蹈教育",
      "planCount": 2,
      "durationYears": 4,
      "tuitionPerYear": 10350,
      "campus": null,
      "remarks": "舞蹈类,师范类,4 年,10350 元/年",
      "pdfPage": 73,
      "bookPage": 23
    },
    {
      "track": "history",
      "batchName": "本科提前批艺术类本科第二批",
      "schoolCode": "10518",
      "schoolName": "汉江师范学院",
      "schoolTotalPlan": 12,
      "schoolLocation": "湖北省十堰市",
      "consultPhone": "0719-8846111、8846222",
      "majorGroupCode": "210",
      "majorGroupPlan": 2,
      "firstSubject": "历史",
      "secondSubject": "不限",
      "majorCode": "006",
      "majorName": "书法学",
      "planCount": 2,
      "durationYears": 4,
      "tuitionPerYear": 10350,
      "campus": null,
      "remarks": "书法类,4 年,10350 元/年",
      "pdfPage": 73,
      "bookPage": 23
    },
    {
      "track": "history",
      "batchName": "本科普通批",
      "schoolCode": "10518",
      "schoolName": "汉江师范学院",
      "schoolTotalPlan": 12,
      "schoolLocation": "湖北省十堰市",
      "consultPhone": "0719-8846111、8846222",
      "majorGroupCode": "108",
      "majorGroupPlan": 12,
      "firstSubject": "历史",
      "secondSubject": "不限",
      "majorCode": "031",
      "majorName": "艺术教育",
      "planCount": 2,
      "durationYears": 4,
      "tuitionPerYear": 4000,
      "campus": null,
      "remarks": "师范类，4 年，4000 元/年",
      "pdfPage": 185,
      "bookPage": 135
    },
    {
      "track": "history",
      "batchName": "本科普通批",
      "schoolCode": "10518",
      "schoolName": "汉江师范学院",
      "schoolTotalPlan": 12,
      "schoolLocation": "湖北省十堰市",
      "consultPhone": "0719-8846111、8846222",
      "majorGroupCode": "108",
      "majorGroupPlan": 12,
      "firstSubject": "历史",
      "secondSubject": "不限",
      "majorCode": "032",
      "majorName": "学前教育",
      "planCount": 2,
      "durationYears": 4,
      "tuitionPerYear": 4000,
      "campus": null,
      "remarks": "师范类，4 年，4000 元/年",
      "pdfPage": 185,
      "bookPage": 135
    },
    {
      "track": "history",
      "batchName": "本科普通批",
      "schoolCode": "10518",
      "schoolName": "汉江师范学院",
      "schoolTotalPlan": 12,
      "schoolLocation": "湖北省十堰市",
      "consultPhone": "0719-8846111、8846222",
      "majorGroupCode": "108",
      "majorGroupPlan": 12,
      "firstSubject": "历史",
      "secondSubject": "不限",
      "majorCode": "033",
      "majorName": "小学教育",
      "planCount": 2,
      "durationYears": 4,
      "tuitionPerYear": 4000,
      "campus": null,
      "remarks": "师范类，4 年，4000 元/年",
      "pdfPage": 185,
      "bookPage": 135
    },
    {
      "track": "history",
      "batchName": "本科普通批",
      "schoolCode": "10518",
      "schoolName": "汉江师范学院",
      "schoolTotalPlan": 12,
      "schoolLocation": "湖北省十堰市",
      "consultPhone": "0719-8846111、8846222",
      "majorGroupCode": "108",
      "majorGroupPlan": 12,
      "firstSubject": "历史",
      "secondSubject": "不限",
      "majorCode": "034",
      "majorName": "汉语言文学",
      "planCount": 2,
      "durationYears": 4,
      "tuitionPerYear": 4000,
      "campus": null,
      "remarks": "师范类，4 年，4000 元/年",
      "pdfPage": 185,
      "bookPage": 135
    },
    {
      "track": "history",
      "batchName": "本科普通批",
      "schoolCode": "10518",
      "schoolName": "汉江师范学院",
      "schoolTotalPlan": 12,
      "schoolLocation": "湖北省十堰市",
      "consultPhone": "0719-8846111、8846222",
      "majorGroupCode": "108",
      "majorGroupPlan": 12,
      "firstSubject": "历史",
      "secondSubject": "不限",
      "majorCode": "035",
      "majorName": "英语",
      "planCount": 2,
      "durationYears": 4,
      "tuitionPerYear": 4000,
      "campus": null,
      "remarks": "师范类，4 年，4000 元/年，要求外语语种为英语",
      "pdfPage": 185,
      "bookPage": 135
    },
    {
      "track": "history",
      "batchName": "本科普通批",
      "schoolCode": "10518",
      "schoolName": "汉江师范学院",
      "schoolTotalPlan": 12,
      "schoolLocation": "湖北省十堰市",
      "consultPhone": "0719-8846111、8846222",
      "majorGroupCode": "108",
      "majorGroupPlan": 12,
      "firstSubject": "历史",
      "secondSubject": "不限",
      "majorCode": "036",
      "majorName": "历史学",
      "planCount": 2,
      "durationYears": 4,
      "tuitionPerYear": 4000,
      "campus": null,
      "remarks": "师范类，4 年，4000 元/年",
      "pdfPage": 185,
      "bookPage": 135
    },
    {
      "track": "history",
      "batchName": "本科普通批",
      "schoolCode": "10518",
      "schoolName": "汉江师范学院",
      "schoolTotalPlan": 12,
      "schoolLocation": "湖北省十堰市",
      "consultPhone": "0719-8846111、8846222",
      "majorGroupCode": "109",
      "majorGroupPlan": 12,
      "firstSubject": "历史",
      "secondSubject": "不限",
      "majorCode": "037",
      "majorName": "日语",
      "planCount": 2,
      "durationYears": 4,
      "tuitionPerYear": 4000,
      "campus": null,
      "remarks": "4 年，4000 元/年",
      "pdfPage": 185,
      "bookPage": 135
    },
    {
      "track": "history",
      "batchName": "本科普通批",
      "schoolCode": "10518",
      "schoolName": "汉江师范学院",
      "schoolTotalPlan": 12,
      "schoolLocation": "湖北省十堰市",
      "consultPhone": "0719-8846111、8846222",
      "majorGroupCode": "109",
      "majorGroupPlan": 12,
      "firstSubject": "历史",
      "secondSubject": "不限",
      "majorCode": "038",
      "majorName": "商务英语",
      "planCount": 2,
      "durationYears": 4,
      "tuitionPerYear": 4000,
      "campus": null,
      "remarks": "4 年，4000 元/年，要求外语语种为英语",
      "pdfPage": 185,
      "bookPage": 135
    },
    {
      "track": "history",
      "batchName": "本科普通批",
      "schoolCode": "10518",
      "schoolName": "汉江师范学院",
      "schoolTotalPlan": 12,
      "schoolLocation": "湖北省十堰市",
      "consultPhone": "0719-8846111、8846222",
      "majorGroupCode": "109",
      "majorGroupPlan": 12,
      "firstSubject": "历史",
      "secondSubject": "不限",
      "majorCode": "039",
      "majorName": "网络与新媒体",
      "planCount": 2,
      "durationYears": 4,
      "tuitionPerYear": 5200,
      "campus": null,
      "remarks": "4 年，5200 元/年",
      "pdfPage": 185,
      "bookPage": 135
    },
    {
      "track": "history",
      "batchName": "本科普通批",
      "schoolCode": "10518",
      "schoolName": "汉江师范学院",
      "schoolTotalPlan": 12,
      "schoolLocation": "湖北省十堰市",
      "consultPhone": "0719-8846111、8846222",
      "majorGroupCode": "109",
      "majorGroupPlan": 12,
      "firstSubject": "历史",
      "secondSubject": "不限",
      "majorCode": "040",
      "majorName": "行政管理",
      "planCount": 2,
      "durationYears": 4,
      "tuitionPerYear": 4000,
      "campus": null,
      "remarks": "4 年, 4000 元/年",
      "pdfPage": 186,
      "bookPage": 136
    },
    {
      "track": "history",
      "batchName": "本科普通批",
      "schoolCode": "10518",
      "schoolName": "汉江师范学院",
      "schoolTotalPlan": 12,
      "schoolLocation": "湖北省十堰市",
      "consultPhone": "0719-8846111、8846222",
      "majorGroupCode": "109",
      "majorGroupPlan": 12,
      "firstSubject": "历史",
      "secondSubject": "不限",
      "majorCode": "041",
      "majorName": "旅游管理",
      "planCount": 2,
      "durationYears": 4,
      "tuitionPerYear": 5200,
      "campus": null,
      "remarks": "4 年，5200 元/年",
      "pdfPage": 186,
      "bookPage": 136
    },
    {
      "track": "history",
      "batchName": "本科普通批",
      "schoolCode": "10518",
      "schoolName": "汉江师范学院",
      "schoolTotalPlan": 12,
      "schoolLocation": "湖北省十堰市",
      "consultPhone": "0719-8846111、8846222",
      "majorGroupCode": "109",
      "majorGroupPlan": 12,
      "firstSubject": "历史",
      "secondSubject": "不限",
      "majorCode": "042",
      "majorName": "广播电视编导",
      "planCount": 2,
      "durationYears": 4,
      "tuitionPerYear": 10350,
      "campus": null,
      "remarks": "4 年，10350 元/年",
      "pdfPage": 186,
      "bookPage": 136
    },
    {
      "track": "history",
      "batchName": "本科普通批",
      "schoolCode": "10518",
      "schoolName": "汉江师范学院",
      "schoolTotalPlan": 12,
      "schoolLocation": "湖北省十堰市",
      "consultPhone": "0719-8846111、8846222",
      "majorGroupCode": "110",
      "majorGroupPlan": 2,
      "firstSubject": "历史",
      "secondSubject": "思想政治",
      "majorCode": "043",
      "majorName": "思想政治教育",
      "planCount": 2,
      "durationYears": 4,
      "tuitionPerYear": 4000,
      "campus": null,
      "remarks": "师范类，4 年，4000 元/年",
      "pdfPage": 186,
      "bookPage": 136
    },
    {
      "track": "history",
      "batchName": "高职高专普通批",
      "schoolCode": "10518",
      "schoolName": "汉江师范学院",
      "schoolTotalPlan": 12,
      "schoolLocation": "湖北省十堰市",
      "consultPhone": "0719-8846111、8846222",
      "majorGroupCode": "117",
      "majorGroupPlan": 2,
      "firstSubject": "历史",
      "secondSubject": "不限",
      "majorCode": "050",
      "majorName": "网络新闻与传播",
      "planCount": 2,
      "durationYears": 3,
      "tuitionPerYear": 4000,
      "campus": "丹江口校区办学",
      "remarks": "3 年,4000 元/年,在丹江口校区办学",
      "pdfPage": 316,
      "bookPage": 266
    }
  ]
}
