{
  "school": {
    "schoolCode": "11105",
    "schoolName": "中国人民警察大学",
    "schoolTotalPlan": 17,
    "schoolLocation": "河北省廊坊市",
    "consultPhone": "0316-2068235",
    "programCount": 10,
    "track": "history"
  },
  "programs": [
    {
      "track": "history",
      "batchName": "本科提前批其他二类",
      "schoolCode": "11105",
      "schoolName": "中国人民警察大学",
      "schoolTotalPlan": 17,
      "schoolLocation": "河北省廊坊市",
      "consultPhone": "0316-2068235",
      "majorGroupCode": "801",
      "majorGroupPlan": 15,
      "firstSubject": "历史",
      "secondSubject": "思想政治",
      "majorCode": "001",
      "majorName": "边防管理(移民方向)",
      "planCount": 2,
      "durationYears": 4,
      "tuitionPerYear": 4900,
      "campus": null,
      "remarks": "4年，4900元/年，只招男生，面向移民管理机构入警就业。具体标准和要求详见警察大学2026年《招生章程》",
      "pdfPage": 126,
      "bookPage": 76
    },
    {
      "track": "history",
      "batchName": "本科提前批其他二类",
      "schoolCode": "11105",
      "schoolName": "中国人民警察大学",
      "schoolTotalPlan": 17,
      "schoolLocation": "河北省廊坊市",
      "consultPhone": "0316-2068235",
      "majorGroupCode": "801",
      "majorGroupPlan": 15,
      "firstSubject": "历史",
      "secondSubject": "思想政治",
      "majorCode": "002",
      "majorName": "涉外警务(地方公安方向)",
      "planCount": 2,
      "durationYears": 4,
      "tuitionPerYear": 4900,
      "campus": null,
      "remarks": "4年，4900元/年，只招男生，面向地方公安机关入警就业。外语成绩须达到外语单科总分的70%。具体标准和要求详见警察大学2026年《招生章程》",
      "pdfPage": 126,
      "bookPage": 76
    },
    {
      "track": "history",
      "batchName": "本科提前批其他二类",
      "schoolCode": "11105",
      "schoolName": "中国人民警察大学",
      "schoolTotalPlan": 17,
      "schoolLocation": "河北省廊坊市",
      "consultPhone": "0316-2068235",
      "majorGroupCode": "801",
      "majorGroupPlan": 15,
      "firstSubject": "历史",
      "secondSubject": "思想政治",
      "majorCode": "003",
      "majorName": "警务指挥与战术(地方公安方向)",
      "planCount": 2,
      "durationYears": 4,
      "tuitionPerYear": 4900,
      "campus": null,
      "remarks": "4 年, 4900 元/年, 只招男生，面向地方公安机关入警就业。具体标准和要求详见警察大学 2026 年《招生章程》",
      "pdfPage": 126,
      "bookPage": 76
    },
    {
      "track": "history",
      "batchName": "本科提前批其他二类",
      "schoolCode": "11105",
      "schoolName": "中国人民警察大学",
      "schoolTotalPlan": 17,
      "schoolLocation": "河北省廊坊市",
      "consultPhone": "0316-2068235",
      "majorGroupCode": "801",
      "majorGroupPlan": 15,
      "firstSubject": "历史",
      "secondSubject": "思想政治",
      "majorCode": "004",
      "majorName": "公安政治工作(地方公安方向)",
      "planCount": 2,
      "durationYears": 4,
      "tuitionPerYear": 4900,
      "campus": null,
      "remarks": "4年，4900元/年，只招男生，面向地方公安机关入警就业。具体标准和要求详见警察大学2026年《招生章程》",
      "pdfPage": 126,
      "bookPage": 76
    },
    {
      "track": "history",
      "batchName": "本科提前批其他二类",
      "schoolCode": "11105",
      "schoolName": "中国人民警察大学",
      "schoolTotalPlan": 17,
      "schoolLocation": "河北省廊坊市",
      "consultPhone": "0316-2068235",
      "majorGroupCode": "801",
      "majorGroupPlan": 15,
      "firstSubject": "历史",
      "secondSubject": "思想政治",
      "majorCode": "005",
      "majorName": "公安政治工作(铁路公安方向)",
      "planCount": 1,
      "durationYears": 4,
      "tuitionPerYear": 4900,
      "campus": null,
      "remarks": "4年，4900元/年，只招男生，面向铁路公安机关入警就业。具体标准和要求详见警察大学2026年《招生章程》",
      "pdfPage": 126,
      "bookPage": 76
    },
    {
      "track": "history",
      "batchName": "本科提前批其他二类",
      "schoolCode": "11105",
      "schoolName": "中国人民警察大学",
      "schoolTotalPlan": 17,
      "schoolLocation": "河北省廊坊市",
      "consultPhone": "0316-2068235",
      "majorGroupCode": "801",
      "majorGroupPlan": 15,
      "firstSubject": "历史",
      "secondSubject": "思想政治",
      "majorCode": "006",
      "majorName": "移民管理(移民方向)",
      "planCount": 2,
      "durationYears": 4,
      "tuitionPerYear": 4900,
      "campus": null,
      "remarks": "4 年,4900 元/年,只招男生，面向移民管理机构入警就业。具体标准和要求详见警察大学 2026 年《招生章程》",
      "pdfPage": 126,
      "bookPage": 76
    },
    {
      "track": "history",
      "batchName": "本科提前批其他二类",
      "schoolCode": "11105",
      "schoolName": "中国人民警察大学",
      "schoolTotalPlan": 17,
      "schoolLocation": "河北省廊坊市",
      "consultPhone": "0316-2068235",
      "majorGroupCode": "801",
      "majorGroupPlan": 15,
      "firstSubject": "历史",
      "secondSubject": "思想政治",
      "majorCode": "007",
      "majorName": "出入境管理(地方公安方向)",
      "planCount": 3,
      "durationYears": 4,
      "tuitionPerYear": 4900,
      "campus": null,
      "remarks": "4年，4900元/年，只招男生，面向地方公安机关入警就业。具体标准和要求详见警察大学2026年《招生章程》",
      "pdfPage": 126,
      "bookPage": 76
    },
    {
      "track": "history",
      "batchName": "本科提前批其他二类",
      "schoolCode": "11105",
      "schoolName": "中国人民警察大学",
      "schoolTotalPlan": 17,
      "schoolLocation": "河北省廊坊市",
      "consultPhone": "0316-2068235",
      "majorGroupCode": "801",
      "majorGroupPlan": 15,
      "firstSubject": "历史",
      "secondSubject": "思想政治",
      "majorCode": "008",
      "majorName": "出入境管理(移民方向)",
      "planCount": 1,
      "durationYears": 4,
      "tuitionPerYear": 4900,
      "campus": null,
      "remarks": "4年,4900元/年,只招男生，面向移民管理机构入警就业。具体标准和要求详见警察大学2026年《招生章程》",
      "pdfPage": 126,
      "bookPage": 76
    },
    {
      "track": "history",
      "batchName": "本科提前批其他二类",
      "schoolCode": "11105",
      "schoolName": "中国人民警察大学",
      "schoolTotalPlan": 17,
      "schoolLocation": "河北省廊坊市",
      "consultPhone": "0316-2068235",
      "majorGroupCode": "802",
      "majorGroupPlan": 2,
      "firstSubject": "历史",
      "secondSubject": "思想政治",
      "majorCode": "009",
      "majorName": "警务指挥与战术(地方公安方向)",
      "planCount": 1,
      "durationYears": 4,
      "tuitionPerYear": 4900,
      "campus": null,
      "remarks": "4 年, 4900 元/年, 只招女生，面向地方公安机关入警就业。具体标准和要求详见警察大学 2026 年《招生章程》",
      "pdfPage": 126,
      "bookPage": 76
    },
    {
      "track": "history",
      "batchName": "本科提前批其他二类",
      "schoolCode": "11105",
      "schoolName": "中国人民警察大学",
      "schoolTotalPlan": 17,
      "schoolLocation": "河北省廊坊市",
      "consultPhone": "0316-2068235",
      "majorGroupCode": "802",
      "majorGroupPlan": 2,
      "firstSubject": "历史",
      "secondSubject": "思想政治",
      "majorCode": "010",
      "majorName": "公安政治工作(地方公安方向)",
      "planCount": 1,
      "durationYears": 4,
      "tuitionPerYear": 4900,
      "campus": null,
      "remarks": "4年，4900元/年，只招女生，面向地方公安机关入警就业。具体标准和要求详见警察大学2026年《招生章程》",
      "pdfPage": 126,
      "bookPage": 76
    }
  ]
}
