{
  "school": {
    "schoolCode": "11445",
    "schoolName": "黑龙江工业学院",
    "schoolTotalPlan": 77,
    "schoolLocation": "黑龙江省鸡西市",
    "consultPhone": "0467-2395188",
    "programCount": 10,
    "track": "history"
  },
  "programs": [
    {
      "track": "history",
      "batchName": "本科普通批",
      "schoolCode": "11445",
      "schoolName": "黑龙江工业学院",
      "schoolTotalPlan": 77,
      "schoolLocation": "黑龙江省鸡西市",
      "consultPhone": "0467-2395188",
      "majorGroupCode": "108",
      "majorGroupPlan": 28,
      "firstSubject": "历史",
      "secondSubject": "不限",
      "majorCode": "019",
      "majorName": "商务经济学",
      "planCount": 9,
      "durationYears": 4,
      "tuitionPerYear": 4500,
      "campus": null,
      "remarks": "4 年, 4500 元/年",
      "pdfPage": 233,
      "bookPage": 183
    },
    {
      "track": "history",
      "batchName": "本科普通批",
      "schoolCode": "11445",
      "schoolName": "黑龙江工业学院",
      "schoolTotalPlan": 77,
      "schoolLocation": "黑龙江省鸡西市",
      "consultPhone": "0467-2395188",
      "majorGroupCode": "108",
      "majorGroupPlan": 28,
      "firstSubject": "历史",
      "secondSubject": "不限",
      "majorCode": "020",
      "majorName": "财务管理",
      "planCount": 12,
      "durationYears": 4,
      "tuitionPerYear": 4500,
      "campus": null,
      "remarks": "4 年，4500 元/年",
      "pdfPage": 233,
      "bookPage": 183
    },
    {
      "track": "history",
      "batchName": "本科普通批",
      "schoolCode": "11445",
      "schoolName": "黑龙江工业学院",
      "schoolTotalPlan": 77,
      "schoolLocation": "黑龙江省鸡西市",
      "consultPhone": "0467-2395188",
      "majorGroupCode": "108",
      "majorGroupPlan": 28,
      "firstSubject": "历史",
      "secondSubject": "不限",
      "majorCode": "021",
      "majorName": "跨境电子商务",
      "planCount": 7,
      "durationYears": 4,
      "tuitionPerYear": "待定",
      "campus": null,
      "remarks": "4年，学费待定",
      "pdfPage": 233,
      "bookPage": 183
    },
    {
      "track": "history",
      "batchName": "本科普通批",
      "schoolCode": "11445",
      "schoolName": "黑龙江工业学院",
      "schoolTotalPlan": 77,
      "schoolLocation": "黑龙江省鸡西市",
      "consultPhone": "0467-2395188",
      "majorGroupCode": "109",
      "majorGroupPlan": 24,
      "firstSubject": "历史",
      "secondSubject": "不限",
      "majorCode": "022",
      "majorName": "国际经贸规则",
      "planCount": 6,
      "durationYears": 4,
      "tuitionPerYear": 4500,
      "campus": null,
      "remarks": "4年，4500元/年",
      "pdfPage": 233,
      "bookPage": 183
    },
    {
      "track": "history",
      "batchName": "本科普通批",
      "schoolCode": "11445",
      "schoolName": "黑龙江工业学院",
      "schoolTotalPlan": 77,
      "schoolLocation": "黑龙江省鸡西市",
      "consultPhone": "0467-2395188",
      "majorGroupCode": "109",
      "majorGroupPlan": 24,
      "firstSubject": "历史",
      "secondSubject": "不限",
      "majorCode": "023",
      "majorName": "学前教育",
      "planCount": 6,
      "durationYears": 4,
      "tuitionPerYear": 4000,
      "campus": null,
      "remarks": "师范类，4年，4000元/年",
      "pdfPage": 233,
      "bookPage": 183
    },
    {
      "track": "history",
      "batchName": "本科普通批",
      "schoolCode": "11445",
      "schoolName": "黑龙江工业学院",
      "schoolTotalPlan": 77,
      "schoolLocation": "黑龙江省鸡西市",
      "consultPhone": "0467-2395188",
      "majorGroupCode": "109",
      "majorGroupPlan": 24,
      "firstSubject": "历史",
      "secondSubject": "不限",
      "majorCode": "024",
      "majorName": "秘书学",
      "planCount": 6,
      "durationYears": 4,
      "tuitionPerYear": 4000,
      "campus": null,
      "remarks": "4 年, 4000 元/年",
      "pdfPage": 233,
      "bookPage": 183
    },
    {
      "track": "history",
      "batchName": "本科普通批",
      "schoolCode": "11445",
      "schoolName": "黑龙江工业学院",
      "schoolTotalPlan": 77,
      "schoolLocation": "黑龙江省鸡西市",
      "consultPhone": "0467-2395188",
      "majorGroupCode": "109",
      "majorGroupPlan": 24,
      "firstSubject": "历史",
      "secondSubject": "不限",
      "majorCode": "025",
      "majorName": "网络与新媒体",
      "planCount": 6,
      "durationYears": 4,
      "tuitionPerYear": 4000,
      "campus": null,
      "remarks": "4年，4000元/年",
      "pdfPage": 233,
      "bookPage": 183
    },
    {
      "track": "history",
      "batchName": "本科普通批",
      "schoolCode": "11445",
      "schoolName": "黑龙江工业学院",
      "schoolTotalPlan": 77,
      "schoolLocation": "黑龙江省鸡西市",
      "consultPhone": "0467-2395188",
      "majorGroupCode": "110",
      "majorGroupPlan": 19,
      "firstSubject": "历史",
      "secondSubject": "不限",
      "majorCode": "026",
      "majorName": "俄语",
      "planCount": 11,
      "durationYears": 4,
      "tuitionPerYear": 4500,
      "campus": null,
      "remarks": "4年，4500元/年",
      "pdfPage": 233,
      "bookPage": 183
    },
    {
      "track": "history",
      "batchName": "本科普通批",
      "schoolCode": "11445",
      "schoolName": "黑龙江工业学院",
      "schoolTotalPlan": 77,
      "schoolLocation": "黑龙江省鸡西市",
      "consultPhone": "0467-2395188",
      "majorGroupCode": "110",
      "majorGroupPlan": 19,
      "firstSubject": "历史",
      "secondSubject": "不限",
      "majorCode": "027",
      "majorName": "商务英语",
      "planCount": 8,
      "durationYears": 4,
      "tuitionPerYear": 4500,
      "campus": null,
      "remarks": "4年，4500元/年，要求外语语种为英语",
      "pdfPage": 233,
      "bookPage": 183
    },
    {
      "track": "history",
      "batchName": "本科普通批",
      "schoolCode": "11445",
      "schoolName": "黑龙江工业学院",
      "schoolTotalPlan": 77,
      "schoolLocation": "黑龙江省鸡西市",
      "consultPhone": "0467-2395188",
      "majorGroupCode": "111",
      "majorGroupPlan": 6,
      "firstSubject": "历史",
      "secondSubject": "思想政治",
      "majorCode": "028",
      "majorName": "中国共产党历史",
      "planCount": 6,
      "durationYears": 4,
      "tuitionPerYear": 4500,
      "campus": null,
      "remarks": "4 年, 4500 元/年",
      "pdfPage": 233,
      "bookPage": 183
    }
  ]
}
