{
  "school": {
    "schoolCode": "13677",
    "schoolName": "西安交通大学城市学院",
    "schoolTotalPlan": 10,
    "schoolLocation": "陕西省西安市",
    "consultPhone": "029-86652009",
    "programCount": 3,
    "track": "history"
  },
  "programs": [
    {
      "track": "history",
      "batchName": "本科普通批",
      "schoolCode": "13677",
      "schoolName": "西安交通大学城市学院",
      "schoolTotalPlan": 10,
      "schoolLocation": "陕西省西安市",
      "consultPhone": "029-86652009",
      "majorGroupCode": "103",
      "majorGroupPlan": 10,
      "firstSubject": "历史",
      "secondSubject": "不限",
      "majorCode": "011",
      "majorName": "金融学",
      "planCount": 4,
      "durationYears": 4,
      "tuitionPerYear": 25300,
      "campus": null,
      "remarks": "4 年,25300 元/年",
      "pdfPage": 274,
      "bookPage": 224
    },
    {
      "track": "history",
      "batchName": "本科普通批",
      "schoolCode": "13677",
      "schoolName": "西安交通大学城市学院",
      "schoolTotalPlan": 10,
      "schoolLocation": "陕西省西安市",
      "consultPhone": "029-86652009",
      "majorGroupCode": "103",
      "majorGroupPlan": 10,
      "firstSubject": "历史",
      "secondSubject": "不限",
      "majorCode": "012",
      "majorName": "网络与新媒体",
      "planCount": 2,
      "durationYears": 4,
      "tuitionPerYear": 25300,
      "campus": null,
      "remarks": "4 年，25300 元/年",
      "pdfPage": 274,
      "bookPage": 224
    },
    {
      "track": "history",
      "batchName": "本科普通批",
      "schoolCode": "13677",
      "schoolName": "西安交通大学城市学院",
      "schoolTotalPlan": 10,
      "schoolLocation": "陕西省西安市",
      "consultPhone": "029-86652009",
      "majorGroupCode": "103",
      "majorGroupPlan": 10,
      "firstSubject": "历史",
      "secondSubject": "不限",
      "majorCode": "013",
      "majorName": "会计学",
      "planCount": 4,
      "durationYears": 4,
      "tuitionPerYear": 25300,
      "campus": null,
      "remarks": "4 年，25300 元/年",
      "pdfPage": 274,
      "bookPage": 224
    }
  ]
}
