{
  "school": {
    "schoolCode": "13736",
    "schoolName": "陕西邮电职业技术学院",
    "schoolTotalPlan": 4,
    "schoolLocation": "陕西省咸阳市",
    "consultPhone": "029-33733333",
    "programCount": 4,
    "track": "history"
  },
  "programs": [
    {
      "track": "history",
      "batchName": "高职高专普通批",
      "schoolCode": "13736",
      "schoolName": "陕西邮电职业技术学院",
      "schoolTotalPlan": 4,
      "schoolLocation": "陕西省咸阳市",
      "consultPhone": "029-33733333",
      "majorGroupCode": "101",
      "majorGroupPlan": 4,
      "firstSubject": "历史",
      "secondSubject": "不限",
      "majorCode": "001",
      "majorName": "应急救援技术",
      "planCount": 1,
      "durationYears": 3,
      "tuitionPerYear": 6500,
      "campus": null,
      "remarks": "3 年,6500 元/年",
      "pdfPage": 370,
      "bookPage": 320
    },
    {
      "track": "history",
      "batchName": "高职高专普通批",
      "schoolCode": "13736",
      "schoolName": "陕西邮电职业技术学院",
      "schoolTotalPlan": 4,
      "schoolLocation": "陕西省咸阳市",
      "consultPhone": "029-33733333",
      "majorGroupCode": "101",
      "majorGroupPlan": 4,
      "firstSubject": "历史",
      "secondSubject": "不限",
      "majorCode": "002",
      "majorName": "数字媒体技术",
      "planCount": 1,
      "durationYears": 3,
      "tuitionPerYear": 6500,
      "campus": null,
      "remarks": "3 年,6500 元/年",
      "pdfPage": 370,
      "bookPage": 320
    },
    {
      "track": "history",
      "batchName": "高职高专普通批",
      "schoolCode": "13736",
      "schoolName": "陕西邮电职业技术学院",
      "schoolTotalPlan": 4,
      "schoolLocation": "陕西省咸阳市",
      "consultPhone": "029-33733333",
      "majorGroupCode": "101",
      "majorGroupPlan": 4,
      "firstSubject": "历史",
      "secondSubject": "不限",
      "majorCode": "003",
      "majorName": "现代移动通信技术",
      "planCount": 1,
      "durationYears": 3,
      "tuitionPerYear": 6500,
      "campus": null,
      "remarks": "3 年,6500 元/年",
      "pdfPage": 370,
      "bookPage": 320
    },
    {
      "track": "history",
      "batchName": "高职高专普通批",
      "schoolCode": "13736",
      "schoolName": "陕西邮电职业技术学院",
      "schoolTotalPlan": 4,
      "schoolLocation": "陕西省咸阳市",
      "consultPhone": "029-33733333",
      "majorGroupCode": "101",
      "majorGroupPlan": 4,
      "firstSubject": "历史",
      "secondSubject": "不限",
      "majorCode": "004",
      "majorName": "大数据与会计",
      "planCount": 1,
      "durationYears": 3,
      "tuitionPerYear": 6500,
      "campus": null,
      "remarks": "3 年,6500 元/年",
      "pdfPage": 370,
      "bookPage": 320
    }
  ]
}
