{
  "school": {
    "schoolCode": "13767",
    "schoolName": "厦门演艺职业学院",
    "schoolTotalPlan": 25,
    "schoolLocation": "福建省厦门市",
    "consultPhone": "0592-3668015",
    "programCount": 6,
    "track": "history"
  },
  "programs": [
    {
      "track": "history",
      "batchName": "高职高专提前批艺术类",
      "schoolCode": "13767",
      "schoolName": "厦门演艺职业学院",
      "schoolTotalPlan": 25,
      "schoolLocation": "福建省厦门市",
      "consultPhone": "0592-3668015",
      "majorGroupCode": "200",
      "majorGroupPlan": 11,
      "firstSubject": "历史",
      "secondSubject": "不限",
      "majorCode": "001",
      "majorName": "音乐表演",
      "planCount": 5,
      "durationYears": 3,
      "tuitionPerYear": 18400,
      "campus": null,
      "remarks": "音乐类（音乐表演），3 年，18400 元/年，声乐方向仅限：声乐（美声、民族）；器乐方向仅限钢琴、古筝、打击乐、古埙、陶笛、吉他、键盘、电贝司方向",
      "pdfPage": 300,
      "bookPage": 250
    },
    {
      "track": "history",
      "batchName": "高职高专提前批艺术类",
      "schoolCode": "13767",
      "schoolName": "厦门演艺职业学院",
      "schoolTotalPlan": 25,
      "schoolLocation": "福建省厦门市",
      "consultPhone": "0592-3668015",
      "majorGroupCode": "200",
      "majorGroupPlan": 11,
      "firstSubject": "历史",
      "secondSubject": "不限",
      "majorCode": "002",
      "majorName": "现代流行音乐",
      "planCount": 6,
      "durationYears": 3,
      "tuitionPerYear": 18400,
      "campus": null,
      "remarks": "音乐类（音乐表演），3 年，18400 元/年，声乐方向仅限：声乐（流行）；器乐方向仅限吉他、电贝司、打击乐、键盘方向",
      "pdfPage": 300,
      "bookPage": 250
    },
    {
      "track": "history",
      "batchName": "高职高专提前批艺术类",
      "schoolCode": "13767",
      "schoolName": "厦门演艺职业学院",
      "schoolTotalPlan": 25,
      "schoolLocation": "福建省厦门市",
      "consultPhone": "0592-3668015",
      "majorGroupCode": "201",
      "majorGroupPlan": 3,
      "firstSubject": "历史",
      "secondSubject": "不限",
      "majorCode": "003",
      "majorName": "音乐剧表演",
      "planCount": 3,
      "durationYears": 3,
      "tuitionPerYear": 18400,
      "campus": null,
      "remarks": "音乐类（音乐表演），3 年，18400 元/年",
      "pdfPage": 300,
      "bookPage": 250
    },
    {
      "track": "history",
      "batchName": "高职高专提前批艺术类",
      "schoolCode": "13767",
      "schoolName": "厦门演艺职业学院",
      "schoolTotalPlan": 25,
      "schoolLocation": "福建省厦门市",
      "consultPhone": "0592-3668015",
      "majorGroupCode": "202",
      "majorGroupPlan": 2,
      "firstSubject": "历史",
      "secondSubject": "不限",
      "majorCode": "004",
      "majorName": "戏剧影视表演",
      "planCount": 2,
      "durationYears": 3,
      "tuitionPerYear": 18400,
      "campus": null,
      "remarks": "表（导）演类（戏剧影视表演），3 年，18400 元/年",
      "pdfPage": 300,
      "bookPage": 250
    },
    {
      "track": "history",
      "batchName": "高职高专提前批艺术类",
      "schoolCode": "13767",
      "schoolName": "厦门演艺职业学院",
      "schoolTotalPlan": 25,
      "schoolLocation": "福建省厦门市",
      "consultPhone": "0592-3668015",
      "majorGroupCode": "203",
      "majorGroupPlan": 9,
      "firstSubject": "历史",
      "secondSubject": "不限",
      "majorCode": "005",
      "majorName": "舞蹈表演",
      "planCount": 4,
      "durationYears": 3,
      "tuitionPerYear": 20700,
      "campus": null,
      "remarks": "舞蹈类，3 年，20700 元/年",
      "pdfPage": 300,
      "bookPage": 250
    },
    {
      "track": "history",
      "batchName": "高职高专提前批艺术类",
      "schoolCode": "13767",
      "schoolName": "厦门演艺职业学院",
      "schoolTotalPlan": 25,
      "schoolLocation": "福建省厦门市",
      "consultPhone": "0592-3668015",
      "majorGroupCode": "203",
      "majorGroupPlan": 9,
      "firstSubject": "历史",
      "secondSubject": "不限",
      "majorCode": "006",
      "majorName": "国际标准舞",
      "planCount": 5,
      "durationYears": 3,
      "tuitionPerYear": 20700,
      "campus": null,
      "remarks": "舞蹈类，3年，20700元/年",
      "pdfPage": 300,
      "bookPage": 250
    }
  ]
}
