{
  "school": {
    "schoolCode": "14761",
    "schoolName": "广东肇庆航空职业学院",
    "schoolTotalPlan": 15,
    "schoolLocation": "广东省肇庆市",
    "consultPhone": "0758-6110088",
    "programCount": 5,
    "track": "history"
  },
  "programs": [
    {
      "track": "history",
      "batchName": "高职高专普通批",
      "schoolCode": "14761",
      "schoolName": "广东肇庆航空职业学院",
      "schoolTotalPlan": 15,
      "schoolLocation": "广东省肇庆市",
      "consultPhone": "0758-6110088",
      "majorGroupCode": "101",
      "majorGroupPlan": 15,
      "firstSubject": "历史",
      "secondSubject": "不限",
      "majorCode": "001",
      "majorName": "无人机应用技术",
      "planCount": 3,
      "durationYears": 3,
      "tuitionPerYear": 20200,
      "campus": null,
      "remarks": "3年,20200元/年",
      "pdfPage": 423,
      "bookPage": 373
    },
    {
      "track": "history",
      "batchName": "高职高专普通批",
      "schoolCode": "14761",
      "schoolName": "广东肇庆航空职业学院",
      "schoolTotalPlan": 15,
      "schoolLocation": "广东省肇庆市",
      "consultPhone": "0758-6110088",
      "majorGroupCode": "101",
      "majorGroupPlan": 15,
      "firstSubject": "历史",
      "secondSubject": "不限",
      "majorCode": "002",
      "majorName": "空中乘务",
      "planCount": 3,
      "durationYears": 3,
      "tuitionPerYear": 20200,
      "campus": null,
      "remarks": "3年,20200元/年",
      "pdfPage": 423,
      "bookPage": 373
    },
    {
      "track": "history",
      "batchName": "高职高专普通批",
      "schoolCode": "14761",
      "schoolName": "广东肇庆航空职业学院",
      "schoolTotalPlan": 15,
      "schoolLocation": "广东省肇庆市",
      "consultPhone": "0758-6110088",
      "majorGroupCode": "101",
      "majorGroupPlan": 15,
      "firstSubject": "历史",
      "secondSubject": "不限",
      "majorCode": "003",
      "majorName": "民航安全技术管理",
      "planCount": 3,
      "durationYears": 3,
      "tuitionPerYear": 20200,
      "campus": null,
      "remarks": "3年,20200元/年",
      "pdfPage": 423,
      "bookPage": 373
    },
    {
      "track": "history",
      "batchName": "高职高专普通批",
      "schoolCode": "14761",
      "schoolName": "广东肇庆航空职业学院",
      "schoolTotalPlan": 15,
      "schoolLocation": "广东省肇庆市",
      "consultPhone": "0758-6110088",
      "majorGroupCode": "101",
      "majorGroupPlan": 15,
      "firstSubject": "历史",
      "secondSubject": "不限",
      "majorCode": "004",
      "majorName": "飞机机电设备维修",
      "planCount": 3,
      "durationYears": 3,
      "tuitionPerYear": 20200,
      "campus": null,
      "remarks": "3年,20200元/年",
      "pdfPage": 423,
      "bookPage": 373
    },
    {
      "track": "history",
      "batchName": "高职高专普通批",
      "schoolCode": "14761",
      "schoolName": "广东肇庆航空职业学院",
      "schoolTotalPlan": 15,
      "schoolLocation": "广东省肇庆市",
      "consultPhone": "0758-6110088",
      "majorGroupCode": "101",
      "majorGroupPlan": 15,
      "firstSubject": "历史",
      "secondSubject": "不限",
      "majorCode": "005",
      "majorName": "护理",
      "planCount": 3,
      "durationYears": 3,
      "tuitionPerYear": 19800,
      "campus": null,
      "remarks": "3年,19800元/年",
      "pdfPage": 423,
      "bookPage": 373
    }
  ]
}
